{
  "version": "1.0",
  "generated_at": "2026-02-08T14:18:40.216394Z",
  "project_name": "test_open_the_black_box",
  "description": "Project 'test_open_the_black_box' using api, git, python and more with 29 development actions recorded.",
  "tech_stack": [
    "api",
    "git",
    "python",
    "testing"
  ],
  "recent_focus": "updated, data_loader, analysis",
  "keywords": [
    "057788z",
    "09t19",
    "09t20",
    "104790z",
    "10t13",
    "13t14",
    "16t09",
    "174662z",
    "187306z",
    "2025",
    "243323z",
    "281148z",
    "507825z",
    "553770z",
    "601896z",
    "700435z",
    "706773z",
    "716755z",
    "738993z",
    "749100z"
  ],
  "confidence": 1.0,
  "readme": {
    "preview": "🧠 Enter The Black Box\n\nA Machine Learning Robustness Lab for Evolving Cyber Attacks\n(Stress-Testing ML Models for Cybersecurity Drift, Mutation & Resilience)\n\n---\n\n--\n\n> ⚙️ *Note: This is a special test project created to demonstrate and test the capabilities of the LazyDeve agent, including synchronization, file management, and AI-assisted development.*\n\n---\n\n## ⭐ Overview\nEnter The Black Box is a research ML platform designed to analyze the robustness of cybersecurity models against evolving attack patterns.\nIt shows:\n- how traffic or log changes break ML models\n- which features are critical\n- how False Negatives / False Positives grow\n- where the model becomes blind\n- how it behaves under data drift, noise injection, and adversarial perturbations.\n\nThis is not just an IDS model — it's a lab that helps understand how fragile ML-based cybersecurity systems can be and how to improve them.\n\n---\n\n## 🏗 Architecture\n\n---\n\n## 🎯 Key Features\n- Baseline ML IDS model (RandomForest/XGBoost)\n- Attack Mutation Engine (drop features, add noise, create drift, mutate patterns)\n- Data Drift Detection (Evidently AI, Alibi Detect)\n- Concept Drift Detection\n- Adversarial Sample Simulation\n- Robustness Scoring & Metrics Comparison\n- Explainability (SHAP)\n- Interactive Streamlit Dashboard\n- MLflow Experiment Tracking\n- Clear reports for SOC / Threat Research teams\n\n---",
    "last_updated": "2026-02-01T11:39:38.962274Z",
    "checksum": "23b1d4df69b322c3c88b4cf94b76a2a1"
  },
  "commits": {
    "last_commit": {
      "version": "1.0",
      "commit_id": "b6f81a3",
      "commit_id_full": "b6f81a3a8fd76b878cefb16edb168e7601d9f15d",
      "files_changed": [
        ".lazydeve/commit_history.json",
        ".lazydeve/context.db",
        ".lazydeve/context_full.json"
      ],
      "summary": "[LazyDeve] auto: Startup commit (test_open_the_black_box)",
      "timestamp": "2026-02-08T14:18:40.146061Z",
      "project": "test_open_the_black_box",
      "body": ""
    },
    "recent": [
      {
        "version": "1.0",
        "commit_id": "b6f81a3",
        "commit_id_full": "b6f81a3a8fd76b878cefb16edb168e7601d9f15d",
        "files_changed": [
          ".lazydeve/commit_history.json",
          ".lazydeve/context.db",
          ".lazydeve/context_full.json"
        ],
        "summary": "[LazyDeve] auto: Startup commit (test_open_the_black_box)",
        "timestamp": "2026-02-08T14:18:40.146061Z",
        "project": "test_open_the_black_box",
        "body": ""
      },
      {
        "version": "1.0",
        "commit_id": "20d9985",
        "commit_id_full": "20d99855709e79d6301c5f8659629c398eb22d52",
        "files_changed": [
          ".lazydeve/commit_history.json",
          ".lazydeve/context.db",
          ".lazydeve/context_full.json"
        ],
        "summary": "[LazyDeve] auto: Startup commit (test_open_the_black_box)",
        "timestamp": "2026-02-08T14:18:40.146061Z",
        "project": "test_open_the_black_box",
        "body": ""
      },
      {
        "version": "1.0",
        "commit_id": "3a4833c",
        "commit_id_full": "3a4833cb1dab01d8ebd352162669f28e12cdba79",
        "files_changed": [
          ".lazydeve/commit_history.json",
          ".lazydeve/context.db",
          ".lazydeve/context_full.json"
        ],
        "summary": "[LazyDeve] auto: Startup commit (test_open_the_black_box)",
        "timestamp": "2026-02-08T14:18:40.146061Z",
        "project": "test_open_the_black_box",
        "body": ""
      }
    ]
  },
  "activity": {
    "total_actions": 29,
    "recent_focus": "updated, data_loader, analysis",
    "common_operations": [
      "execute",
      "add_test",
      "analyze",
      "create",
      "commit"
    ],
    "error_patterns": [],
    "recent_actions": [
      {
        "time": "2026-02-04T20:44:35.378574Z",
        "action": "Executed: aider_task: Explain the architecture and main components of th (failed) - Process timed out after 60 seconds",
        "status": "failed"
      },
      {
        "time": "2026-01-06T13:53:31.115493Z",
        "action": "Updated: README.md",
        "status": "ok"
      },
      {
        "time": "2026-01-06T13:39:17.121938Z",
        "action": "Updated: README.md",
        "status": "ok"
      },
      {
        "time": "2025-12-16T09:57:02.706773Z",
        "action": "Executed: Add a note to the project memory using /api/v1/con",
        "status": "ok"
      },
      {
        "time": "2025-12-13T14:36:51.738993Z",
        "action": "Updated: test_3.py",
        "status": "ok"
      }
    ]
  },
  "snapshot": {
    "last_run": "2025-12-13T16:43:03.382633Z",
    "status": "unknown",
    "pending_changes": false
  },
  "config": {
    "git_repo_path": "C:\\Users\\LENOVO\\Desktop\\Python\\LazyDeve\\projects\\test_open_the_black_box",
    "git_initialized": "2025-12-09T20:45:45.209241"
  },
  "stats": {
    "commits": 1,
    "executions": 16,
    "analyses": 3,
    "total_actions": 32
  },
  "user_memory": null
}